osa_tool/__init__.py
osa_tool/aboutgen/__init__.py
osa_tool/aboutgen/about_generator.py
osa_tool/aboutgen/prompts_about_config.py
osa_tool/analytics/__init__.py
osa_tool/analytics/metadata.py
osa_tool/analytics/prompt_builder.py
osa_tool/analytics/report_generator.py
osa_tool/analytics/report_maker.py
osa_tool/analytics/run_report_gen.py
osa_tool/analytics/sourcerank.py
osa_tool/arguments_parser.py
osa_tool/config/__init__.py
osa_tool/config/settings/arguments.yaml
osa_tool/config/settings/config.toml
osa_tool/config/settings/prompt_for_analysis.toml
osa_tool/config/settings/prompt_for_scheduler.toml
osa_tool/config/settings/prompts.toml
osa_tool/config/settings/prompts_about_section.toml
osa_tool/config/settings/prompts_article.toml
osa_tool/config/settings.py
osa_tool/config/templates/template.toml
osa_tool/config/templates/workflow/github_gitverse/autopep8.yml
osa_tool/config/templates/workflow/github_gitverse/black.yml
osa_tool/config/templates/workflow/github_gitverse/fix_pep8.yml
osa_tool/config/templates/workflow/github_gitverse/pep8.yml
osa_tool/config/templates/workflow/github_gitverse/pypi_publish.yml
osa_tool/config/templates/workflow/github_gitverse/slash_command_dispatch.yml
osa_tool/config/templates/workflow/github_gitverse/unit_test.yml
osa_tool/config/templates/workflow/gitlab/autopep8.yml
osa_tool/config/templates/workflow/gitlab/black.yml
osa_tool/config/templates/workflow/gitlab/fix_pep8.yml
osa_tool/config/templates/workflow/gitlab/pep8.yml
osa_tool/config/templates/workflow/gitlab/pypi_publish.yml
osa_tool/config/templates/workflow/gitlab/slash_command_dispatch.yml
osa_tool/config/templates/workflow/gitlab/unit_test.yml
osa_tool/convertion/__init__.py
osa_tool/convertion/notebook_converter.py
osa_tool/docs/images/osa_logo.PNG
osa_tool/docs/images/osa_logo_transparent.PNG
osa_tool/docs/templates/ci_config.toml
osa_tool/docs/templates/community.toml
osa_tool/docs/templates/contributing.toml
osa_tool/docs/templates/licenses.toml
osa_tool-0.2.3.dist-info/METADATA
osa_tool-0.2.3.dist-info/WHEEL
osa_tool-0.2.3.dist-info/entry_points.txt
osa_tool-0.2.3.dist-info/licenses/LICENSE
osa_tool-0.2.3.dist-info/RECORD
