Metadata-Version: 2.4
Name: osa_tool
Version: 0.2.3
Summary: Tool that just makes your open source project better!
License-Expression: BSD-3-Clause
License-File: LICENSE
Author: ITMO-NSS-team
Author-email: itmo.nss.team@gmail.com
Requires-Python: >=3.10,<4.0
Classifier: Programming Language :: Python :: 3
Classifier: Programming Language :: Python :: 3.10
Classifier: Programming Language :: Python :: 3.11
Classifier: Programming Language :: Python :: 3.12
Classifier: Programming Language :: Python :: 3.13
Classifier: Programming Language :: Python :: 3.14
Requires-Dist: ProtoLLM (>=0.1.5)
Requires-Dist: PyYAML (==6.0.2)
Requires-Dist: Pygments (==2.19.1)
Requires-Dist: aiofiles (>=24.1.0,<25.0.0)
Requires-Dist: aiohappyeyeballs (==2.4.4)
Requires-Dist: aiohttp (==3.11.11)
Requires-Dist: aiosignal (==1.3.2)
Requires-Dist: annotated-types (==0.7.0)
Requires-Dist: anyio (==4.7.0)
Requires-Dist: async-timeout (>=4.0.0,<5.0.0)
Requires-Dist: attrs (==25.1.0)
Requires-Dist: black (==25.1.0)
Requires-Dist: certifi (==2024.12.14)
Requires-Dist: charset-normalizer (==3.4.1)
Requires-Dist: colorama (==0.4.6)
Requires-Dist: distro (==1.9.0)
Requires-Dist: exceptiongroup (==1.2.2)
Requires-Dist: frozenlist (==1.5.0)
Requires-Dist: gitdb (==4.0.11)
Requires-Dist: gitpython (==3.1.43)
Requires-Dist: h11 (==0.16.0)
Requires-Dist: httpcore (==1.0.9)
Requires-Dist: httpx (>=0.27.2,<0.28.0)
Requires-Dist: idna (==3.10)
Requires-Dist: iniconfig (==2.0.0)
Requires-Dist: jiter (==0.8.2)
Requires-Dist: markdown-it-py (==3.0.0)
Requires-Dist: mdurl (==0.1.2)
Requires-Dist: mkdocs (==1.6.1)
Requires-Dist: mkdocs-material (==9.6.13)
Requires-Dist: mkdocstrings[python] (==0.29.1)
Requires-Dist: multidict (==6.1.0)
Requires-Dist: nbconvert (>=6.0)
Requires-Dist: nbformat (>=5.0)
Requires-Dist: openai (==1.58.1)
Requires-Dist: openpyxl (==3.1.5)
Requires-Dist: packaging (==24.2)
Requires-Dist: pandas (==2.2.3)
Requires-Dist: pdfminer.six (==20231228)
Requires-Dist: pdfplumber (==0.11.5)
Requires-Dist: pipreqs (>=0.5.0,<0.6.0) ; python_version < "3.13"
Requires-Dist: pluggy (==1.5.0)
Requires-Dist: prompt_toolkit (==3.0.51)
Requires-Dist: propcache (==0.2.1)
Requires-Dist: pydantic (>=2.9.0,<2.11.0)
Requires-Dist: pydantic-extra-types (==2.9.0)
Requires-Dist: pydantic_core (>=2.23.4,<2.24.0)
Requires-Dist: pytest (==8.3.4)
Requires-Dist: pytest-asyncio (==1.1.0)
Requires-Dist: pytest-mock (==3.14.0)
Requires-Dist: python-dotenv (==1.0.1)
Requires-Dist: qrcode (==8.0)
Requires-Dist: regex (==2024.11.6)
Requires-Dist: reportlab (==4.3.1)
Requires-Dist: requests (==2.32.3)
Requires-Dist: rich (==13.9.4)
Requires-Dist: smmap (==5.0.2)
Requires-Dist: sniffio (==1.3.1)
Requires-Dist: structlog (==24.4.0)
Requires-Dist: tiktoken (==0.8.0)
Requires-Dist: tomli (==2.2.1)
Requires-Dist: tqdm (==4.67.1)
Requires-Dist: tree-sitter (==0.23.2)
Requires-Dist: tree-sitter-python (==0.23.4)
Requires-Dist: typing_extensions (==4.12.2)
Requires-Dist: urllib3 (==2.3.0)
Requires-Dist: yarl (==1.18.3)
Project-URL: Documentation, https://itmo-nss-team.github.io/Open-Source-Advisor/
Project-URL: Homepage, https://github.com/aimclub/OSA
Project-URL: Issues, https://github.com/aimclub/OSA/issues
